datastory/__init__.py
datastory/datastory.py
datastory-0.1.16.dist-info/LICENSE
datastory-0.1.16.dist-info/METADATA
datastory-0.1.16.dist-info/WHEEL
datastory-0.1.16.dist-info/RECORD
