Metadata-Version: 2.1
Name: datastory
Version: 0.1.16
Summary: 
Author: nada developers
Author-email: nada@nav.no
Requires-Python: >=3.7,<4.0
Classifier: Programming Language :: Python :: 3
Classifier: Programming Language :: Python :: 3.7
Classifier: Programming Language :: Python :: 3.8
Classifier: Programming Language :: Python :: 3.9
Classifier: Programming Language :: Python :: 3.10
Classifier: Programming Language :: Python :: 3.11
Requires-Dist: requests (>=2.26.0,<3.0.0)
